youtube_transcript_api_sentences/__init__.py
youtube_transcript_api_sentences/__main__.py
youtube_transcript_api_sentences/_api.py
youtube_transcript_api_sentences/_cli.py
youtube_transcript_api_sentences/_errors.py
youtube_transcript_api_sentences/_settings.py
youtube_transcript_api_sentences/_transcripts.py
youtube_transcript_api_sentences/formatters.py
youtube_transcript_api_sentences/proxies.py
youtube_transcript_api_sentences/py.typed
youtube_transcript_api_sentences/test/__init__.py
youtube_transcript_api_sentences/test/assets/__init__.py
youtube_transcript_api_sentences/test/assets/example_cookies.txt
youtube_transcript_api_sentences/test/assets/expired_example_cookies.txt
youtube_transcript_api_sentences/test/assets/transcript.xml.static
youtube_transcript_api_sentences/test/assets/youtube.html.static
youtube_transcript_api_sentences/test/assets/youtube_age_restricted.html.static
youtube_transcript_api_sentences/test/assets/youtube_altered_user_agent.html.static
youtube_transcript_api_sentences/test/assets/youtube_consent_page.html.static
youtube_transcript_api_sentences/test/assets/youtube_consent_page_invalid.html.static
youtube_transcript_api_sentences/test/assets/youtube_no_translation_languages.html.static
youtube_transcript_api_sentences/test/assets/youtube_request_blocked.html.static
youtube_transcript_api_sentences/test/assets/youtube_too_many_requests.html.static
youtube_transcript_api_sentences/test/assets/youtube_transcripts_disabled.html.static
youtube_transcript_api_sentences/test/assets/youtube_transcripts_disabled2.html.static
youtube_transcript_api_sentences/test/assets/youtube_unplayable.html.static
youtube_transcript_api_sentences/test/assets/youtube_video_unavailable.html.static
youtube_transcript_api_sentences/test/assets/youtube_ww1_nl_en.html.static
youtube_transcript_api_sentences/test/test_api.py
youtube_transcript_api_sentences/test/test_cli.py
youtube_transcript_api_sentences/test/test_formatters.py
youtube_transcript_api_sentences-0.1.1.dist-info/LICENSE
youtube_transcript_api_sentences-0.1.1.dist-info/METADATA
youtube_transcript_api_sentences-0.1.1.dist-info/WHEEL
youtube_transcript_api_sentences-0.1.1.dist-info/entry_points.txt
youtube_transcript_api_sentences-0.1.1.dist-info/RECORD
