Metadata-Version: 2.3
Name: youtube-transcript-api-sentences
Version: 0.1.1
Summary: A fork of youtube-transcript-api that groups captions into complete sentences
Keywords: youtube,transcript,api,captions,subtitles,sentences
Author: Ahaan Limaye
Author-email: ahaan.limaye@gmail.com
Requires-Python: >=3.8,<3.14
Classifier: Development Status :: 4 - Beta
Classifier: Intended Audience :: Developers
Classifier: License :: OSI Approved :: MIT License
Classifier: Programming Language :: Python :: 3
Classifier: Programming Language :: Python :: 3.8
Classifier: Programming Language :: Python :: 3.9
Classifier: Programming Language :: Python :: 3.10
Classifier: Programming Language :: Python :: 3.11
Classifier: Programming Language :: Python :: 3.12
Classifier: Programming Language :: Python :: 3.13
Requires-Dist: defusedxml (>=0.7.1,<0.8.0)
Requires-Dist: requests
Project-URL: Documentation, https://github.com/ahaanlimaye/youtube-transcript-api#readme
Project-URL: Repository, https://github.com/ahaanlimaye/youtube-transcript-api
